README.md
setup.cfg
setup.py
FakesUsers/FakesUsers.py
FakesUsers/__init__.py
FakesUsers.egg-info/PKG-INFO
FakesUsers.egg-info/SOURCES.txt
FakesUsers.egg-info/dependency_links.txt
FakesUsers.egg-info/requires.txt
FakesUsers.egg-info/top_level.txt