Metadata-Version: 2.1
Name: FakesUsers
Version: 3.0
Summary: FakesUsers - Python library that regenerates random names, phone numbers and addresses. For now, only the Russian generation is available, but over time we will add other generations.
Author: filcher2011
Author-email: filcher2011@mail.ru
Keywords: FakesUsers
Requires-Python: >=3.7
Requires-Dist: requests>=2.25.1
